setup.py
data_uri/__init__.py
data_uri/__main__.py
data_uri/encoder.py
data_uri.egg-info/PKG-INFO
data_uri.egg-info/SOURCES.txt
data_uri.egg-info/dependency_links.txt
data_uri.egg-info/entry_points.txt
data_uri.egg-info/requires.txt
data_uri.egg-info/top_level.txt