Metadata-Version: 1.0
Name: data-uri
Version: 0.0.2
Summary: Data-URI Encoder/Decoder
Home-page: UNKNOWN
Author: Shane R. Spencer
Author-email: shane@bogomip.com
License: MIT
Platform: UNKNOWN
